jupyterlab_urdf/__init__.py
jupyterlab_urdf/_version.py
jupyterlab_urdf-0.6.0.data/data/share/jupyter/labextensions/jupyterlab-urdf/package.json
jupyterlab_urdf-0.6.0.data/data/share/jupyter/labextensions/jupyterlab-urdf/static/177.cd882e37228cb788d5d8.js
jupyterlab_urdf-0.6.0.data/data/share/jupyter/labextensions/jupyterlab-urdf/static/19.83437927b77ffcb327a3.js
jupyterlab_urdf-0.6.0.data/data/share/jupyter/labextensions/jupyterlab-urdf/static/728.af06ea0892275de0443e.js
jupyterlab_urdf-0.6.0.data/data/share/jupyter/labextensions/jupyterlab-urdf/static/85.4eee5396bd9f5ecb7fb7.js
jupyterlab_urdf-0.6.0.data/data/share/jupyter/labextensions/jupyterlab-urdf/static/907.f27c7e22d11f2617d050.js
jupyterlab_urdf-0.6.0.data/data/share/jupyter/labextensions/jupyterlab-urdf/static/924.656a9e9a9a50ee7e3b99.js
jupyterlab_urdf-0.6.0.data/data/share/jupyter/labextensions/jupyterlab-urdf/static/964.16bbe1972549e9415bf8.js
jupyterlab_urdf-0.6.0.data/data/share/jupyter/labextensions/jupyterlab-urdf/static/964.16bbe1972549e9415bf8.js.LICENSE.txt
jupyterlab_urdf-0.6.0.data/data/share/jupyter/labextensions/jupyterlab-urdf/static/remoteEntry.11936c224c170fa20178.js
jupyterlab_urdf-0.6.0.data/data/share/jupyter/labextensions/jupyterlab-urdf/static/style.js
jupyterlab_urdf-0.6.0.data/data/share/jupyter/labextensions/jupyterlab-urdf/static/third-party-licenses.json
jupyterlab_urdf-0.6.0.data/data/share/jupyter/labextensions/jupyterlab-urdf/install.json
jupyterlab_urdf-0.6.0.dist-info/METADATA
jupyterlab_urdf-0.6.0.dist-info/WHEEL
jupyterlab_urdf-0.6.0.dist-info/licenses/LICENSE
jupyterlab_urdf-0.6.0.dist-info/RECORD
