Metadata-Version: 2.4
Name: jupyterlab_urdf
Version: 0.6.0
Dynamic: Keywords
Summary: A URDF viewer and editor extension for JupyterLab.
Project-URL: Homepage, https://github.com/jupyter-robotics/jupyterlab-urdf
Project-URL: Bug Tracker, https://github.com/jupyter-robotics/jupyterlab-urdf/issues
Project-URL: Repository, https://github.com/jupyter-robotics/jupyterlab-urdf.git
Author-email: Isabel Paredes <isabel.paredes@quantstack.net>
License: BSD 3-Clause License
License-File: LICENSE
Classifier: Framework :: Jupyter
Classifier: Framework :: Jupyter :: JupyterLab
Classifier: Framework :: Jupyter :: JupyterLab :: 4
Classifier: Framework :: Jupyter :: JupyterLab :: Extensions
Classifier: Framework :: Jupyter :: JupyterLab :: Extensions :: Prebuilt
Classifier: License :: OSI Approved :: BSD License
Classifier: Programming Language :: Python
Classifier: Programming Language :: Python :: 3
Classifier: Programming Language :: Python :: 3.8
Classifier: Programming Language :: Python :: 3.9
Classifier: Programming Language :: Python :: 3.10
Classifier: Programming Language :: Python :: 3.11
Requires-Python: >=3.8
